<?xml version="1.0" encoding="UTF-8"?>
<objects serializationModel="Studio.02.02.00">
	<object class="AudioFile" id="{c6a3366c-3c1e-4fae-8431-8dca9d5a1242}">
		<property name="assetPath">
			<value>General/Footsteps/Pool/6.wav</value>
		</property>
		<property name="frequencyInKHz">
			<value>44.0999985</value>
		</property>
		<property name="channelCount">
			<value>1</value>
		</property>
		<property name="length">
			<value>0.44535147392290247</value>
		</property>
		<relationship name="masterAssetFolder">
			<destination>{1dc979b3-1c30-40f6-befc-0387ca49d968}</destination>
		</relationship>
	</object>
</objects>
